README.md
setup.py
PackerBuilder.egg-info/PKG-INFO
PackerBuilder.egg-info/SOURCES.txt
PackerBuilder.egg-info/dependency_links.txt
PackerBuilder.egg-info/requires.txt
PackerBuilder.egg-info/top_level.txt
examples/__init__.py
examples/ami_builder.py
packerpy/__init__.py
packerpy/builder.py
packerpy/client.py
packerpy/exceptions.py
packerpy/models.py
packerpy/util.py
tests/__init__.py
tests/test.py