Metadata-Version: 2.1
Name: PackerBuilder
Version: 1.0.3
Summary: Packer for python
Home-page: https://github.com/sroomberg/packerpy
Author: sroomberg
Author-email: stevenroomberg@gmail.com
License: BSD 3-Clause License
Platform: UNKNOWN
Classifier: Programming Language :: Python :: 3
Classifier: License :: OSI Approved :: BSD License
Classifier: Operating System :: OS Independent
Requires-Python: >=3.8
